{
	"configurations" : 
	[
		{
			"directories" : 
			[
				{
					"build" : ".",
					"hasInstallRule" : true,
					"jsonFile" : "directory-.-485ce75ca313d4c82564.json",
					"minimumCMakeVersion" : 
					{
						"string" : "3.12"
					},
					"projectIndex" : 0,
					"source" : ".",
					"targetIndexes" : 
					[
						0,
						1,
						2,
						3,
						4,
						5,
						6,
						7
					]
				}
			],
			"name" : "",
			"projects" : 
			[
				{
					"directoryIndexes" : 
					[
						0
					],
					"name" : "my_first_pkg",
					"targetIndexes" : 
					[
						0,
						1,
						2,
						3,
						4,
						5,
						6,
						7
					]
				}
			],
			"targets" : 
			[
				{
					"directoryIndex" : 0,
					"id" : "add_client::@6890427a1f51a3e7e1df",
					"jsonFile" : "target-add_client-9218da525f3298c5bbd4.json",
					"name" : "add_client",
					"projectIndex" : 0
				},
				{
					"directoryIndex" : 0,
					"id" : "add_server::@6890427a1f51a3e7e1df",
					"jsonFile" : "target-add_server-b1a4b242b619c1303dfb.json",
					"name" : "add_server",
					"projectIndex" : 0
				},
				{
					"directoryIndex" : 0,
					"id" : "ekf_slam::@6890427a1f51a3e7e1df",
					"jsonFile" : "target-ekf_slam-d3cfc2f18e41697fe056.json",
					"name" : "ekf_slam",
					"projectIndex" : 0
				},
				{
					"directoryIndex" : 0,
					"id" : "listener::@6890427a1f51a3e7e1df",
					"jsonFile" : "target-listener-3f7a7c8545d5bac322ca.json",
					"name" : "listener",
					"projectIndex" : 0
				},
				{
					"directoryIndex" : 0,
					"id" : "my_first_pkg_uninstall::@6890427a1f51a3e7e1df",
					"jsonFile" : "target-my_first_pkg_uninstall-2fbae796ffe5d445c43d.json",
					"name" : "my_first_pkg_uninstall",
					"projectIndex" : 0
				},
				{
					"directoryIndex" : 0,
					"id" : "sensor_pub::@6890427a1f51a3e7e1df",
					"jsonFile" : "target-sensor_pub-b77c527fed3f4aa28008.json",
					"name" : "sensor_pub",
					"projectIndex" : 0
				},
				{
					"directoryIndex" : 0,
					"id" : "talker::@6890427a1f51a3e7e1df",
					"jsonFile" : "target-talker-03ac4f818855210fa852.json",
					"name" : "talker",
					"projectIndex" : 0
				},
				{
					"directoryIndex" : 0,
					"id" : "uninstall::@6890427a1f51a3e7e1df",
					"jsonFile" : "target-uninstall-b022f536c4f08693416e.json",
					"name" : "uninstall",
					"projectIndex" : 0
				}
			]
		}
	],
	"kind" : "codemodel",
	"paths" : 
	{
		"build" : "/home/yang/Desktop/ros-pr0/build/my_first_pkg",
		"source" : "/home/yang/Desktop/ros-pr0/my_first_pkg"
	},
	"version" : 
	{
		"major" : 2,
		"minor" : 3
	}
}
